LICENSE
MANIFEST.in
README.md
setup.cfg
setup.py
requirements/requirements.txt
src/os_scrapy/VERSION
src/os_scrapy/__init__.py
src/os_scrapy/cmdline.py
src/os_scrapy/patch.py
src/os_scrapy.egg-info/PKG-INFO
src/os_scrapy.egg-info/SOURCES.txt
src/os_scrapy.egg-info/dependency_links.txt
src/os_scrapy.egg-info/entry_points.txt
src/os_scrapy.egg-info/not-zip-safe
src/os_scrapy.egg-info/requires.txt
src/os_scrapy.egg-info/top_level.txt
src/os_scrapy/commands/__init__.py
src/os_scrapy/commands/crawl.py
src/os_scrapy/commands/startproject.py
src/os_scrapy/commands/version.py
src/os_scrapy/settings/__init__.py
src/os_scrapy/settings/default_settings.py
tests/__init__.py
tests/test_version.py